ugoira/__init__.py
ugoira/cli.py
ugoira/lib.py
ugoira-0.10.0.dist-info/LICENSE
ugoira-0.10.0.dist-info/METADATA
ugoira-0.10.0.dist-info/WHEEL
ugoira-0.10.0.dist-info/entry_points.txt
ugoira-0.10.0.dist-info/RECORD
